ps_k8s_ctrl_common/__init__.py
ps_k8s_ctrl_common/ctrl_data.py
ps_k8s_ctrl_common/ps_ctrl.py
ps_k8s_ctrl_common-0.0.0.4.dist-info/METADATA
ps_k8s_ctrl_common-0.0.0.4.dist-info/WHEEL
ps_k8s_ctrl_common-0.0.0.4.dist-info/top_level.txt
ps_k8s_ctrl_common-0.0.0.4.dist-info/RECORD
