Metadata-Version: 2.1
Name: ps-k8s-ctrl-common
Version: 0.0.0.4
Summary: Platform Services Kubernetes Controller Common Functions
Home-page: https://git.viasat.com/Mobility-Engineering/ps-k8s-ctrl_common
Author: Commercial Mobility Engineering
Author-email: cm-wickedsmaht@viasat.com
License: (c) 2022 Viasat, Inc.
Platform: UNKNOWN
Classifier: Programming Language :: Python :: 3
Classifier: License :: OSI Approved :: MIT License
Classifier: Operating System :: OS Independent
